gspot_fastapi_auth/__init__.py
gspot_fastapi_auth/auth.py
gspot_fastapi_auth/base.py
gspot_fastapi_auth/models.py
gspot_fastapi_auth/permissions.py
gspot_fastapi_auth/providers.py
gspot_fastapi_auth/services.py
gspot_fastapi_auth/settings.py
gspot_fastapi_auth/test_factory.py
gspot_fastapi_auth-0.0.6.dist-info/METADATA
gspot_fastapi_auth-0.0.6.dist-info/WHEEL
gspot_fastapi_auth-0.0.6.dist-info/licenses/LICENSE
gspot_fastapi_auth-0.0.6.dist-info/RECORD
